codeserializerlib/__init__.py
codeserializerlib/processing.py
codeserializerlib/model/__init__.py
codeserializerlib/model/config.cfg
codeserializerlib/model/meta.json
codeserializerlib/model/tokenizer
codeserializerlib/model/ner/__init__.py
codeserializerlib/model/ner/cfg
codeserializerlib/model/ner/model
codeserializerlib/model/ner/moves
codeserializerlib/model/tok2vec/__init__.py
codeserializerlib/model/tok2vec/cfg
codeserializerlib/model/tok2vec/model
codeserializerlib/model/vocab/__init__.py
codeserializerlib/model/vocab/key2row
codeserializerlib/model/vocab/lookups.bin
codeserializerlib/model/vocab/strings.json
codeserializerlib/model/vocab/vectors
codeserializerlib/model/vocab/vectors.cfg
codeserializerlib/models/__init__.py
codeserializerlib/models/code.py
codeserializerlib/models/code_type.py
codeserializerlib/models/label.py
tests/__init__.py
tests/test_processing.py
codeserializerlib-1.0.6.dist-info/METADATA
codeserializerlib-1.0.6.dist-info/WHEEL
codeserializerlib-1.0.6.dist-info/top_level.txt
codeserializerlib-1.0.6.dist-info/RECORD
