Metadata-Version: 2.1
Name: codeserializerlib
Version: 1.0.6
Summary: Python library for the code serializer
Author: Tony Meissner
Author-email: tonymeissner70@gmail.com
Requires-Dist: spacy >=3.7.2
